funapi/__init__.py
funidea-0.0.5.dist-info/LICENSE
funidea-0.0.5.dist-info/METADATA
funidea-0.0.5.dist-info/WHEEL
funidea-0.0.5.dist-info/entry_points.txt
funidea-0.0.5.dist-info/top_level.txt
funidea-0.0.5.dist-info/RECORD
