Metadata-Version: 2.1
Name: funidea
Version: 0.0.5
Summary: funidea
Home-page: https://github.com/farfarfun/funidea
Author: bingtao
Author-email: 1007530194@qq.com
License-File: LICENSE
Requires-Dist: funpypi
Requires-Dist: funfile
Requires-Dist: requests
Requires-Dist: tqdm
